energyweb/__init__.py
energyweb/carbonemission.py
energyweb/config.py
energyweb/dispatcher.py
energyweb/interfaces.py
energyweb/log.py
energyweb/storage.py
energyweb/database/__init__.py
energyweb/database/dao.py
energyweb/database/elasticdao.py
energyweb/database/memorydao.py
energyweb/eds/__init__.py
energyweb/eds/energy_api.py
energyweb/eds/eumel.py
energyweb/eds/interfaces.py
energyweb/eds/simulator.py
energyweb/smart_contract/__init__.py
energyweb/smart_contract/interfaces.py
energyweb/smart_contract/origin_v1.py
energyweb/smart_contract/origin/__init__.py
energyweb/smart_contract/origin/asset_reg_v1.py
energyweb/smart_contract/origin/certificate_v1.py
energyweb/smart_contract/origin/consumer_v1.py
energyweb/smart_contract/origin/producer_v1.py
energyweb/smart_contract/usn/__init__.py
energyweb/smart_contract/usn/rent_v1.py
energyweb-0.4.5.dist-info/LICENSE
energyweb-0.4.5.dist-info/METADATA
energyweb-0.4.5.dist-info/WHEEL
energyweb-0.4.5.dist-info/top_level.txt
energyweb-0.4.5.dist-info/RECORD
