Metadata-Version: 2.1
Name: energyweb
Version: 0.4.5
Summary: Energy utility data interface for blockchain smart contracts
Home-page: https://github.com/energywebfoundation/ew-link-bond
Author: github.com/cerealkill
Author-email: paul.depraz@energyweb.org
License: UNKNOWN
Keywords: ethereum,blockchain,energy-web,energy,smart-energy_meter
Platform: UNKNOWN
Classifier: Programming Language :: Python :: 3
Classifier: License :: OSI Approved :: GNU Lesser General Public License v3 or later (LGPLv3+)
Classifier: Operating System :: OS Independent
Classifier: Natural Language :: English
Classifier: Intended Audience :: Science/Research
Classifier: Environment :: Console
Classifier: Development Status :: 2 - Pre-Alpha
Requires-Dist: web3 (<5.0.0,>=4.8.0)
Requires-Dist: colorlog (>=3.1.4)
Requires-Dist: base58 (>=1.0.3)
